cv-metrics/__init__.py
tests/__init__.py
cv_metrics-0.0.1.dist-info/LICENSE
cv_metrics-0.0.1.dist-info/METADATA
cv_metrics-0.0.1.dist-info/WHEEL
cv_metrics-0.0.1.dist-info/top_level.txt
cv_metrics-0.0.1.dist-info/RECORD
