Metadata-Version: 2.1
Name: cv-metrics
Version: 0.0.1
Summary: Metrics To Evaluate Computer Vision Algorithms in Python
Home-page: https://github.com/SkalskiP/cv-metrics
Author: Piotr Skalski
Author-email: piotr.skalski92@gmail.com
License: BSD
Platform: UNKNOWN
